otp_widget/OTPWidgetAPIClient.py
otp_widget/__init__.py
msg9191_otp_widget_python-0.1.0.dist-info/LICENSE
msg9191_otp_widget_python-0.1.0.dist-info/METADATA
msg9191_otp_widget_python-0.1.0.dist-info/WHEEL
msg9191_otp_widget_python-0.1.0.dist-info/top_level.txt
msg9191_otp_widget_python-0.1.0.dist-info/RECORD
