Metadata-Version: 2.1
Name: msg9191-otp-widget-python
Version: 0.1.0
Summary: A client for the OTP Widget API
Home-page: https://github.com/yourusername/otp-widget-python
Author: Harsh jaiswal
Author-email: harshjaiswal@whozzat.com
Classifier: Programming Language :: Python :: 3
Classifier: License :: OSI Approved :: MIT License
Classifier: Operating System :: OS Independent
Requires-Python: >=3.6
License-File: LICENSE
Requires-Dist: requests
